Workbook

Sheet Supuestos
A1: Alternativa 3: utilitario propio con financiamiento INAES. Supuestos del modelo
A2: Moneda constante de septiembre de 2026 (momento 0). Texto azul: dato de entrada. Fondo amarillo: supuesto sobre la cooperativa, a reemplazar por el dato relevado. Texto negro: fórmula.
A4: A. Datos externos relevados
A5: Precio Dongfeng Captain W 412 CD sin IVA | B5: 21891 | C5: USD | D5: Lista de precios Magma/Dongfeng 01/25 (precio público sugerido).
A6: Precio Dongfeng Captain W 412 CD con IVA (10,5 %) | B6: 24190 | C6: USD | D6: Ídem. Pagadero en pesos al tipo vendedor BNA del día anterior al pago.
A7: Tipo de cambio BNA vendedor | B7: 1550 | C7: $/USD | D7: El Cronista, 28/09/2026.
A8: Precio neto en pesos (monto financiable) | B8: =B5*B7 -> 33931050 | C8: $ | D8: El INAES no financia impuestos (Res. 1287/15, Anexo I, pto. 4).
A9: Precio con IVA en pesos | B9: =B6*B7 -> 37494500 | C9: $
A10: IVA de la compra (crédito fiscal) | B10: =B9-B8 -> 3563450 | C10: $ | D10: Recuperable: la cooperativa es responsable inscripta.
A11: Tasa del préstamo INAES (efectiva anual) | B11: 0.06 | D11: Res. INAES 1287/15, Anexo I, pto. 5: 6 % anual efectivo sobre saldos, en pesos.
A12: Tasa del préstamo INAES (efectiva mensual) | B12: =(1+B11)^(1/12)-1 -> 0.0048675506
A13: Bonificación de intereses por pago puntual | B13: 0.5 | D13: Res. 1287/15: 50 % del total de intereses, descontado de las últimas cuotas.
A14: Cantidad de cuotas mensuales | B14: 60 | D14: Máximo admitido por la Res. 1287/15. Sin período de gracia.
A15: Alícuota de patente (pick-up, código B85) | B15: 0.02 | D15: API Santa Fe, Patente Única sobre Vehículos, año fiscal 2026.
A16: Valuación fiscal supuesta del rodado | B16: =B9 -> 37494500 | C16: $ | D16: Se supone igual al precio con IVA y constante en términos reales (criterio conservador).
A17: Revisión técnica obligatoria (por revisión) | B17: 75000 | C17: $ | D17: Tarifa APSV Santa Fe 2026. Primera a los 3 años, luego cada 2 años.
A18: Inflación mensual octubre 2026 | B18: 0.017 | D18: REM BCRA agosto 2026 (mediana).
A19: Inflación mensual noviembre 2026 | B19: 0.016 | D19: REM BCRA agosto 2026 (mediana).
A20: Inflación mensual diciembre 2026 | B20: 0.018 | D20: REM BCRA agosto 2026 (mediana).
A21: Inflación anual 2027 | B21: 0.205 | D21: REM BCRA agosto 2026 (mediana).
A22: Inflación anual 2028 | B22: 0.141 | D22: REM BCRA agosto 2026 (mediana).
A23: Inflación anual 2029 en adelante | B23: 0.141 | D23: El REM no proyecta más allá de 2028: se mantiene la última expectativa disponible.
A24: TAMAR bancos privados septiembre 2026 (TNA) | B24: 0.2411 | D24: REM BCRA agosto 2026.
A25: Inflación esperada próximos 12 meses | B25: 0.21 | D25: REM BCRA agosto 2026.
A26: Tasa real implícita (TAMAR frente a inflación esperada) | B26: =(1+B24/12)^12/(1+B25)-1 -> 0.049264614 | D26: Costo de oportunidad real de los fondos de la cooperativa.
A27: Tasa de descuento real adoptada | B27: 0.05 | D27: Redondeo de B26. Sensibilidad entre 3 % y 10 %.
A28: Seguro mensual del utilitario (uso comercial) | B28: 150000 | C28: $ | D28: Dentro del rango relevado para pick-ups en terceros completo ($120.000 a $170.000 por mes, 2026).
A30: B. Supuestos sobre la cooperativa (a validar con registros internos)
A31: Pago mensual por el vehículo del asociado 1 (auto) | B31: 250000 | C31: $ | D31: Anteproyecto, Capítulo I. Incluye las reparaciones del vehículo.
A32: Pago mensual por el vehículo del asociado 2 (4x4) | B32: 450000 | C32: $ | D32: Anteproyecto, Capítulo I. Incluye las reparaciones del vehículo.
A33: Combustible vehículo 1 (mensual) | B33: 300000 | C33: $ | D33: Supuesto: promedio de los últimos 12 meses.
A34: Combustible vehículo 2, 4x4 (mensual) | B34: 520000 | C34: $ | D34: Supuesto: promedio de los últimos 12 meses.
A35: Proporción del pago del vehículo 2 que se evita | B35: 1 | D35: Supuesto: el utilitario reemplaza por completo a la 4x4; el vehículo 1 continúa.
A36: Combustible mensual del utilitario | B36: =B34 -> 520000 | C36: $ | D36: Supuesto: igual al de la 4x4 reemplazada (mismos recorridos). No hay dato de consumo publicado.
A37: Mantenimiento del utilitario, años 1 y 2 (anual) | B37: 600000 | C37: $ | D37: Supuesto: services oficiales en garantía y neumáticos.
A38: Mantenimiento del utilitario, años 3 a 5 (anual) | B38: 1200000 | C38: $ | D38: Supuesto: fuera de garantía, según registro histórico de reparaciones.
A39: Gastos iniciales (patentamiento, gestión y garantías) | B39: 1500000 | C39: $ | D39: Supuesto: presupuesto de gestoría, escribanía y certificaciones contables.
A40: Valor residual al año 5 (% del precio neto) | B40: 0.4 | D40: Supuesto de valor comercial. Sensibilidad entre 0 % y 55 %.
A41: Proporción del precio neto financiada por INAES | B41: 1 | D41: Supuesto: la solicitud cubre el 100 % del precio neto.
A42: Vida útil contable del rodado (años) | B42: 5 | C42: años | D42: Criterio contable habitual para rodados; coincide con el horizonte.

Sheet Préstamo INAES
A1: Cuadro de amortización del préstamo INAES (sistema francés) y conversión a moneda constante
A3: Monto del préstamo | E3: =Supuestos!B8*Supuestos!B41 -> 33931050
A4: Tasa efectiva mensual | E4: =Supuestos!B12 -> 0.0048675506
A5: Cuota mensual nominal fija | E5: =PMT(E4,Supuestos!B14,-E3) -> 653477.52
A6: Intereses totales | E6: =SUM(F11:F70) -> 5277601
A7: Bonificación total (se descuenta de las últimas cuotas) | E7: =Supuestos!B13*E6 -> 2638800.5
A9: Mes | B9: Año | C9: Inflación mensual | D9: Índice de precios | E9: Saldo inicial | F9: Interés | G9: Amortización | H9: Cuota | I9: Bonificación aplicada | J9: Pago neto | K9: Saldo final | L9: Pago (moneda constante) | M9: Interés (moneda constante) | N9: Amortización (moneda constante) | O9: Bonificación (moneda constante) | P9: RECPAM del préstamo
A10: 0 | B10: 0 | D10: 1 | K10: =E3 -> 33931050
A11: 1 | B11: =ROUNDUP(A11/12,0) -> 1 | C11: =IF(A11=1,Supuestos!$B$18,IF(A11=2,Supuestos!$B$19,IF(A11=3,Supuestos!$B$20,IF(A11<=15,(1+Supuestos!$B$21)^(1/12)-1,IF(A11<=27,(1+Supuestos!$B$22)^(1/12)-1,(1+Supuestos!$B$23)^(1/12)-1))))) -> 0.017 | D11: =D10*(1+C11) -> 1.017 | E11: =K10 -> 33931050 | F11: =E11*$E$4 -> 165161.1 | G11: =H11-F11 -> 488316.42 | H11: =$E$5 -> 653477.52 | I11: =MAX(0,MIN(H11,$E$7-H11*(Supuestos!$B$14-A11))) -> 0 | J11: =H11-I11 -> 653477.52 | K11: =E11-G11 -> 33442734 | L11: =J11/D11 -> 642554.1 | M11: =F11/D11 -> 162400.3 | N11: =G11/D11 -> 480153.8 | O11: =I11/D11 -> 0 | P11: =E11*(1/D10-1/D11) -> 567185.69
A12: 2 | B12: =ROUNDUP(A12/12,0) -> 1 | C12: =IF(A12=1,Supuestos!$B$18,IF(A12=2,Supuestos!$B$19,IF(A12=3,Supuestos!$B$20,IF(A12<=15,(1+Supuestos!$B$21)^(1/12)-1,IF(A12<=27,(1+Supuestos!$B$22)^(1/12)-1,(1+Supuestos!$B$23)^(1/12)-1))))) -> 0.016 | D12: =D11*(1+C12) -> 1.033272 | E12: =K11 -> 33442734 | F12: =E12*$E$4 -> 162784.2 | G12: =H12-F12 -> 490693.32 | H12: =$E$5 -> 653477.52 | I12: =MAX(0,MIN(H12,$E$7-H12*(Supuestos!$B$14-A12))) -> 0 | J12: =H12-I12 -> 653477.52 | K12: =E12-G12 -> 32952040 | L12: =J12/D12 -> 632435.14 | M12: =F12/D12 -> 157542.44 | N12: =G12/D12 -> 474892.69 | O12: =I12/D12 -> 0 | P12: =E12*(1/D11-1/D12) -> 517853.71
A13: 3 | B13: =ROUNDUP(A13/12,0) -> 1 | C13: =IF(A13=1,Supuestos!$B$18,IF(A13=2,Supuestos!$B$19,IF(A13=3,Supuestos!$B$20,IF(A13<=15,(1+Supuestos!$B$21)^(1/12)-1,IF(A13<=27,(1+Supuestos!$B$22)^(1/12)-1,(1+Supuestos!$B$23)^(1/12)-1))))) -> 0.018 | D13: =D12*(1+C13) -> 1.0518709 | E13: =K12 -> 32952040 | F13: =E13*$E$4 -> 160395.72 | G13: =H13-F13 -> 493081.79 | H13: =$E$5 -> 653477.52 | I13: =MAX(0,MIN(H13,$E$7-H13*(Supuestos!$B$14-A13))) -> 0 | J13: =H13-I13 -> 653477.52 | K13: =E13-G13 -> 32458958 | L13: =J13/D13 -> 621252.59 | M13: =F13/D13 -> 152486.13 | N13: =G13/D13 -> 468766.46 | O13: =I13/D13 -> 0 | P13: =E13*(1/D12-1/D13) -> 563887.38
A14: 4 | B14: =ROUNDUP(A14/12,0) -> 1 | C14: =IF(A14=1,Supuestos!$B$18,IF(A14=2,Supuestos!$B$19,IF(A14=3,Supuestos!$B$20,IF(A14<=15,(1+Supuestos!$B$21)^(1/12)-1,IF(A14<=27,(1+Supuestos!$B$22)^(1/12)-1,(1+Supuestos!$B$23)^(1/12)-1))))) -> 0.015661337 | D14: =D13*(1+C14) -> 1.0683446 | E14: =K13 -> 32458958 | F14: =E14*$E$4 -> 157995.62 | G14: =H14-F14 -> 495481.9 | H14: =$E$5 -> 653477.52 | I14: =MAX(0,MIN(H14,$E$7-H14*(Supuestos!$B$14-A14))) -> 0 | J14: =H14-I14 -> 653477.52 | K14: =E14-G14 -> 31963477 | L14: =J14/D14 -> 611672.97 | M14: =F14/D14 -> 147888.26 | N14: =G14/D14 -> 463784.71 | O14: =I14/D14 -> 0 | P14: =E14*(1/D13-1/D14) -> 475830.26
A15: 5 | B15: =ROUNDUP(A15/12,0) -> 1 | C15: =IF(A15=1,Supuestos!$B$18,IF(A15=2,Supuestos!$B$19,IF(A15=3,Supuestos!$B$20,IF(A15<=15,(1+Supuestos!$B$21)^(1/12)-1,IF(A15<=27,(1+Supuestos!$B$22)^(1/12)-1,(1+Supuestos!$B$23)^(1/12)-1))))) -> 0.015661337 | D15: =D14*(1+C15) -> 1.0850763 | E15: =K14 -> 31963477 | F15: =E15*$E$4 -> 155583.84 | G15: =H15-F15 -> 497893.68 | H15: =$E$5 -> 653477.52 | I15: =MAX(0,MIN(H15,$E$7-H15*(Supuestos!$B$14-A15))) -> 0 | J15: =H15-I15 -> 653477.52 | K15: =E15-G15 -> 31465583 | L15: =J15/D15 -> 602241.07 | M15: =F15/D15 -> 143385.16 | N15: =G15/D15 -> 458855.91 | O15: =I15/D15 -> 0 | P15: =E15*(1/D14-1/D15) -> 461341.55
A16: 6 | B16: =ROUNDUP(A16/12,0) -> 1 | C16: =IF(A16=1,Supuestos!$B$18,IF(A16=2,Supuestos!$B$19,IF(A16=3,Supuestos!$B$20,IF(A16<=15,(1+Supuestos!$B$21)^(1/12)-1,IF(A16<=27,(1+Supuestos!$B$22)^(1/12)-1,(1+Supuestos!$B$23)^(1/12)-1))))) -> 0.015661337 | D16: =D15*(1+C16) -> 1.1020701 | E16: =K15 -> 31465583 | F16: =E16*$E$4 -> 153160.32 | G16: =H16-F16 -> 500317.2 | H16: =$E$5 -> 653477.52 | I16: =MAX(0,MIN(H16,$E$7-H16*(Supuestos!$B$14-A16))) -> 0 | J16: =H16-I16 -> 653477.52 | K16: =E16-G16 -> 30965266 | L16: =J16/D16 -> 592954.61 | M16: =F16/D16 -> 138975.12 | N16: =G16/D16 -> 453979.49 | O16: =I16/D16 -> 0 | P16: =E16*(1/D15-1/D16) -> 447152.25
A17: 7 | B17: =ROUNDUP(A17/12,0) -> 1 | C17: =IF(A17=1,Supuestos!$B$18,IF(A17=2,Supuestos!$B$19,IF(A17=3,Supuestos!$B$20,IF(A17<=15,(1+Supuestos!$B$21)^(1/12)-1,IF(A17<=27,(1+Supuestos!$B$22)^(1/12)-1,(1+Supuestos!$B$23)^(1/12)-1))))) -> 0.015661337 | D17: =D16*(1+C17) -> 1.1193299 | E17: =K16 -> 30965266 | F17: =E17*$E$4 -> 150725 | G17: =H17-F17 -> 502752.52 | H17: =$E$5 -> 653477.52 | I17: =MAX(0,MIN(H17,$E$7-H17*(Supuestos!$B$14-A17))) -> 0 | J17: =H17-I17 -> 653477.52 | K17: =E17-G17 -> 30462513 | L17: =J17/D17 -> 583811.34 | M17: =F17/D17 -> 134656.45 | N17: =G17/D17 -> 449154.89 | O17: =I17/D17 -> 0 | P17: =E17*(1/D16-1/D17) -> 433256.94
A18: 8 | B18: =ROUNDUP(A18/12,0) -> 1 | C18: =IF(A18=1,Supuestos!$B$18,IF(A18=2,Supuestos!$B$19,IF(A18=3,Supuestos!$B$20,IF(A18<=15,(1+Supuestos!$B$21)^(1/12)-1,IF(A18<=27,(1+Supuestos!$B$22)^(1/12)-1,(1+Supuestos!$B$23)^(1/12)-1))))) -> 0.015661337 | D18: =D17*(1+C18) -> 1.1368601 | E18: =K17 -> 30462513 | F18: =E18*$E$4 -> 148277.82 | G18: =H18-F18 -> 505199.69 | H18: =$E$5 -> 653477.52 | I18: =MAX(0,MIN(H18,$E$7-H18*(Supuestos!$B$14-A18))) -> 0 | J18: =H18-I18 -> 653477.52 | K18: =E18-G18 -> 29957313 | L18: =J18/D18 -> 574809.06 | M18: =F18/D18 -> 130427.5 | N18: =G18/D18 -> 444381.57 | O18: =I18/D18 -> 0 | P18: =E18*(1/D17-1/D18) -> 419650.29
A19: 9 | B19: =ROUNDUP(A19/12,0) -> 1 | C19: =IF(A19=1,Supuestos!$B$18,IF(A19=2,Supuestos!$B$19,IF(A19=3,Supuestos!$B$20,IF(A19<=15,(1+Supuestos!$B$21)^(1/12)-1,IF(A19<=27,(1+Supuestos!$B$22)^(1/12)-1,(1+Supuestos!$B$23)^(1/12)-1))))) -> 0.015661337 | D19: =D18*(1+C19) -> 1.1546649 | E19: =K18 -> 29957313 | F19: =E19*$E$4 -> 145818.74 | G19: =H19-F19 -> 507658.78 | H19: =$E$5 -> 653477.52 | I19: =MAX(0,MIN(H19,$E$7-H19*(Supuestos!$B$14-A19))) -> 0 | J19: =H19-I19 -> 653477.52 | K19: =E19-G19 -> 29449655 | L19: =J19/D19 -> 565945.6 | M19: =F19/D19 -> 126286.63 | N19: =G19/D19 -> 439658.97 | O19: =I19/D19 -> 0 | P19: =E19*(1/D18-1/D19) -> 406327.05
A20: 10 | B20: =ROUNDUP(A20/12,0) -> 1 | C20: =IF(A20=1,Supuestos!$B$18,IF(A20=2,Supuestos!$B$19,IF(A20=3,Supuestos!$B$20,IF(A20<=15,(1+Supuestos!$B$21)^(1/12)-1,IF(A20<=27,(1+Supuestos!$B$22)^(1/12)-1,(1+Supuestos!$B$23)^(1/12)-1))))) -> 0.015661337 | D20: =D19*(1+C20) -> 1.1727485 | E20: =K19 -> 29449655 | F20: =E20*$E$4 -> 143347.68 | G20: =H20-F20 -> 510129.83 | H20: =$E$5 -> 653477.52 | I20: =MAX(0,MIN(H20,$E$7-H20*(Supuestos!$B$14-A20))) -> 0 | J20: =H20-I20 -> 653477.52 | K20: =E20-G20 -> 28939525 | L20: =J20/D20 -> 557218.81 | M20: =F20/D20 -> 122232.25 | N20: =G20/D20 -> 434986.56 | O20: =I20/D20 -> 0 | P20: =E20*(1/D19-1/D20) -> 393282.08
A21: 11 | B21: =ROUNDUP(A21/12,0) -> 1 | C21: =IF(A21=1,Supuestos!$B$18,IF(A21=2,Supuestos!$B$19,IF(A21=3,Supuestos!$B$20,IF(A21<=15,(1+Supuestos!$B$21)^(1/12)-1,IF(A21<=27,(1+Supuestos!$B$22)^(1/12)-1,(1+Supuestos!$B$23)^(1/12)-1))))) -> 0.015661337 | D21: =D20*(1+C21) -> 1.1911153 | E21: =K20 -> 28939525 | F21: =E21*$E$4 -> 140864.6 | G21: =H21-F21 -> 512612.92 | H21: =$E$5 -> 653477.52 | I21: =MAX(0,MIN(H21,$E$7-H21*(Supuestos!$B$14-A21))) -> 0 | J21: =H21-I21 -> 653477.52 | K21: =E21-G21 -> 28426912 | L21: =J21/D21 -> 548626.58 | M21: =F21/D21 -> 118262.77 | N21: =G21/D21 -> 430363.81 | O21: =I21/D21 -> 0 | P21: =E21*(1/D20-1/D21) -> 380510.31
A22: 12 | B22: =ROUNDUP(A22/12,0) -> 1 | C22: =IF(A22=1,Supuestos!$B$18,IF(A22=2,Supuestos!$B$19,IF(A22=3,Supuestos!$B$20,IF(A22<=15,(1+Supuestos!$B$21)^(1/12)-1,IF(A22<=27,(1+Supuestos!$B$22)^(1/12)-1,(1+Supuestos!$B$23)^(1/12)-1))))) -> 0.015661337 | D22: =D21*(1+C22) -> 1.2097698 | E22: =K21 -> 28426912 | F22: =E22*$E$4 -> 138369.43 | G22: =H22-F22 -> 515108.09 | H22: =$E$5 -> 653477.52 | I22: =MAX(0,MIN(H22,$E$7-H22*(Supuestos!$B$14-A22))) -> 0 | J22: =H22-I22 -> 653477.52 | K22: =E22-G22 -> 27911804 | L22: =J22/D22 -> 540166.85 | M22: =F22/D22 -> 114376.67 | N22: =G22/D22 -> 425790.18 | O22: =I22/D22 -> 0 | P22: =E22*(1/D21-1/D22) -> 368006.76
... A70: 60 | B70: =ROUNDUP(A70/12,0) -> 5 | C70: =IF(A70=1,Supuestos!$B$18,IF(A70=2,Supuestos!$B$19,IF(A70=3,Supuestos!$B$20,IF(A70<=15,(1+Supuestos!$B$21)^(1/12)-1,IF(A70<=27,(1+Supuestos!$B$22)^(1/12)-1,(1+Supuestos!$B$23)^(1/12)-1))))) -> 0.011052724 | D70: =D69*(1+C70) -> 2.0785987 | E70: =K69 -> 650312.09 | F70: =E70*$E$4 -> 3165.427 | G70: =H70-F70 -> 650312.09 | H70: =$E$5 -> 653477.52 | I70: =MAX(0,MIN(H70,$E$7-H70*(Supuestos!$B$14-A70))) -> 653477.52 | J70: =H70-I70 -> 0 | K70: =E70-G70 -> 0 | L70: =J70/D70 -> 0 | M70: =F70/D70 -> 1522.8658 | N70: =G70/D70 -> 312860.82 | O70: =I70/D70 -> 314383.68 | P70: =E70*(1/D69-1/D70) -> 3457.9643
A71: Total | F71: =SUM(F11:F70) -> 5277601 | G71: =SUM(G11:G70) -> 33931050 | H71: =SUM(H11:H70) -> 39208651 | I71: =SUM(I11:I70) -> 2638800.5 | J71: =SUM(J11:J70) -> 36569851 | L71: =SUM(L11:L70) -> 25555398 | M71: =SUM(M11:M70) -> 4006423 | N71: =SUM(N11:N70) -> 22840026 | O71: =SUM(O11:O70) -> 1291050.4 | P71: =SUM(P11:P70) -> 11091024
A73: Moneda constante: importe nominal dividido por el índice de precios del mes (base septiembre 2026 = 1). RECPAM: ganancia por la pérdida de poder adquisitivo del saldo adeudado en pesos.

Sheet Comparación
A1: Costos de transporte: situación actual frente a la alternativa 3 (moneda constante de septiembre 2026)
A3: Concepto | B3: Año 0 | C3: Año 1 | D3: Año 2 | E3: Año 3 | F3: Año 4 | G3: Año 5 | H3: Total
A4: Situación actual (vehículos aportados por asociados)
A5: Pago por el vehículo 1 (auto) | C5: =12*Supuestos!$B$31 -> 3000000 | D5: =12*Supuestos!$B$31 -> 3000000 | E5: =12*Supuestos!$B$31 -> 3000000 | F5: =12*Supuestos!$B$31 -> 3000000 | G5: =12*Supuestos!$B$31 -> 3000000 | H5: =SUM(B5:G5) -> 15000000
A6: Pago por el vehículo 2 (4x4) | C6: =12*Supuestos!$B$32 -> 5400000 | D6: =12*Supuestos!$B$32 -> 5400000 | E6: =12*Supuestos!$B$32 -> 5400000 | F6: =12*Supuestos!$B$32 -> 5400000 | G6: =12*Supuestos!$B$32 -> 5400000 | H6: =SUM(B6:G6) -> 27000000
A7: Combustible vehículos 1 y 2 | C7: =12*(Supuestos!$B$33+Supuestos!$B$34) -> 9840000 | D7: =12*(Supuestos!$B$33+Supuestos!$B$34) -> 9840000 | E7: =12*(Supuestos!$B$33+Supuestos!$B$34) -> 9840000 | F7: =12*(Supuestos!$B$33+Supuestos!$B$34) -> 9840000 | G7: =12*(Supuestos!$B$33+Supuestos!$B$34) -> 9840000 | H7: =SUM(B7:G7) -> 49200000
A8: Total situación actual | C8: =SUM(C5:C7) -> 18240000 | D8: =SUM(D5:D7) -> 18240000 | E8: =SUM(E5:E7) -> 18240000 | F8: =SUM(F5:F7) -> 18240000 | G8: =SUM(G5:G7) -> 18240000 | H8: =SUM(B8:G8) -> 91200000
A10: Alternativa 3 (utilitario propio financiado por INAES)
A11: Pago por el vehículo 1 (continúa) | C11: =12*Supuestos!$B$31 -> 3000000 | D11: =12*Supuestos!$B$31 -> 3000000 | E11: =12*Supuestos!$B$31 -> 3000000 | F11: =12*Supuestos!$B$31 -> 3000000 | G11: =12*Supuestos!$B$31 -> 3000000 | H11: =SUM(B11:G11) -> 15000000
A12: Pago remanente por el vehículo 2 | C12: =12*Supuestos!$B$32*(1-Supuestos!$B$35) -> 0 | D12: =12*Supuestos!$B$32*(1-Supuestos!$B$35) -> 0 | E12: =12*Supuestos!$B$32*(1-Supuestos!$B$35) -> 0 | F12: =12*Supuestos!$B$32*(1-Supuestos!$B$35) -> 0 | G12: =12*Supuestos!$B$32*(1-Supuestos!$B$35) -> 0 | H12: =SUM(B12:G12) -> 0
A13: Combustible vehículo 1 y utilitario | C13: =12*(Supuestos!$B$33+Supuestos!$B$36) -> 9840000 | D13: =12*(Supuestos!$B$33+Supuestos!$B$36) -> 9840000 | E13: =12*(Supuestos!$B$33+Supuestos!$B$36) -> 9840000 | F13: =12*(Supuestos!$B$33+Supuestos!$B$36) -> 9840000 | G13: =12*(Supuestos!$B$33+Supuestos!$B$36) -> 9840000 | H13: =SUM(B13:G13) -> 49200000
A14: Seguro del utilitario | C14: =12*Supuestos!$B$28 -> 1800000 | D14: =12*Supuestos!$B$28 -> 1800000 | E14: =12*Supuestos!$B$28 -> 1800000 | F14: =12*Supuestos!$B$28 -> 1800000 | G14: =12*Supuestos!$B$28 -> 1800000 | H14: =SUM(B14:G14) -> 9000000
A15: Patente del utilitario | C15: =Supuestos!$B$15*Supuestos!$B$16 -> 749890 | D15: =Supuestos!$B$15*Supuestos!$B$16 -> 749890 | E15: =Supuestos!$B$15*Supuestos!$B$16 -> 749890 | F15: =Supuestos!$B$15*Supuestos!$B$16 -> 749890 | G15: =Supuestos!$B$15*Supuestos!$B$16 -> 749890 | H15: =SUM(B15:G15) -> 3749450
A16: Mantenimiento del utilitario | C16: =IF(1<=2,Supuestos!$B$37,Supuestos!$B$38) -> 600000 | D16: =IF(2<=2,Supuestos!$B$37,Supuestos!$B$38) -> 600000 | E16: =IF(3<=2,Supuestos!$B$37,Supuestos!$B$38) -> 1200000 | F16: =IF(4<=2,Supuestos!$B$37,Supuestos!$B$38) -> 1200000 | G16: =IF(5<=2,Supuestos!$B$37,Supuestos!$B$38) -> 1200000 | H16: =SUM(B16:G16) -> 4800000
A17: Revisión técnica obligatoria | C17: =IF(OR(1=3,1=5),Supuestos!$B$17,0) -> 0 | D17: =IF(OR(2=3,2=5),Supuestos!$B$17,0) -> 0 | E17: =IF(OR(3=3,3=5),Supuestos!$B$17,0) -> 75000 | F17: =IF(OR(4=3,4=5),Supuestos!$B$17,0) -> 0 | G17: =IF(OR(5=3,5=5),Supuestos!$B$17,0) -> 75000 | H17: =SUM(B17:G17) -> 150000
A18: Cuotas INAES pagadas (moneda constante) | C18: =SUMIF('Préstamo INAES'!$B$11:$B$70,1,'Préstamo INAES'!$L$11:$L$70) -> 7073688.7 | D18: =SUMIF('Préstamo INAES'!$B$11:$B$70,2,'Préstamo INAES'!$L$11:$L$70) -> 5964728 | E18: =SUMIF('Préstamo INAES'!$B$11:$B$70,3,'Préstamo INAES'!$L$11:$L$70) -> 5221329.1 | F18: =SUMIF('Préstamo INAES'!$B$11:$B$70,4,'Préstamo INAES'!$L$11:$L$70) -> 4576099.1 | G18: =SUMIF('Préstamo INAES'!$B$11:$B$70,5,'Préstamo INAES'!$L$11:$L$70) -> 2719553.5 | H18: =SUM(B18:G18) -> 25555398
A19: Aporte propio inicial (precio con IVA + gastos − préstamo) | B19: =Supuestos!B9+Supuestos!B39-'Préstamo INAES'!E3 -> 5063450 | H19: =SUM(B19:G19) -> 5063450
A20: Recupero del IVA de la compra | C20: =-Supuestos!B10 -> -3563450 | H20: =SUM(B20:G20) -> -3563450
A21: Valor residual del utilitario (se descuenta del costo) | G21: =-Supuestos!B40*Supuestos!B8 -> -13572420 | H21: =SUM(B21:G21) -> -13572420
A22: Total alternativa 3 | B22: =SUM(B11:B21) -> 5063450 | C22: =SUM(C11:C21) -> 19500129 | D22: =SUM(D11:D21) -> 21954618 | E22: =SUM(E11:E21) -> 21886219 | F22: =SUM(F11:F21) -> 21165989 | G22: =SUM(G11:G21) -> 5812023.5 | H22: =SUM(B22:G22) -> 95382428
A24: Ahorro de la alternativa 3 (actual − alternativa) | B24: =N(B8)-B22 -> -5063450 | C24: =N(C8)-C22 -> -1260128.7 | D24: =N(D8)-D22 -> -3714618 | E24: =N(E8)-E22 -> -3646219.1 | F24: =N(F8)-F22 -> -2925989.1 | G24: =N(G8)-G22 -> 12427976 | H24: =SUM(B24:G24) -> -4182428.4
A26: Valor actual de costos (VAC) situación actual | B26: =NPV(Supuestos!$B$27,C8:G8) -> 78969654
A27: Valor actual de costos (VAC) alternativa 3 | B27: =B22+NPV(Supuestos!$B$27,C22:G22) -> 84421810
A28: Diferencia de VAC a favor de la alternativa 3 | B28: =B26-B27 -> -5452155.5
A30: La situación actual no tiene erogaciones en el año 0. La diferencia de VAC coincide con el VAN del flujo del inversionista.

Sheet EERR
A1: Estado de resultados proyectado incremental de la alternativa 3 (moneda constante de septiembre 2026)
A2: Diferencia entre la alternativa 3 y la situación actual. Los ahorros de costos se exponen como ingresos diferenciales.
A4: Concepto | B4: Año 0 | C4: Año 1 | D4: Año 2 | E4: Año 3 | F4: Año 4 | G4: Año 5 | H4: Total
A5: Ahorros de costos
A6: Pagos evitados por el vehículo 2 (4x4) | C6: =12*Supuestos!$B$32*Supuestos!$B$35 -> 5400000 | D6: =12*Supuestos!$B$32*Supuestos!$B$35 -> 5400000 | E6: =12*Supuestos!$B$32*Supuestos!$B$35 -> 5400000 | F6: =12*Supuestos!$B$32*Supuestos!$B$35 -> 5400000 | G6: =12*Supuestos!$B$32*Supuestos!$B$35 -> 5400000 | H6: =SUM(B6:G6) -> 27000000
A7: Diferencia de combustible | C7: =12*(Supuestos!$B$34-Supuestos!$B$36) -> 0 | D7: =12*(Supuestos!$B$34-Supuestos!$B$36) -> 0 | E7: =12*(Supuestos!$B$34-Supuestos!$B$36) -> 0 | F7: =12*(Supuestos!$B$34-Supuestos!$B$36) -> 0 | G7: =12*(Supuestos!$B$34-Supuestos!$B$36) -> 0 | H7: =SUM(B7:G7) -> 0
A8: Total ahorros de costos | C8: =SUM(C6:C7) -> 5400000 | D8: =SUM(D6:D7) -> 5400000 | E8: =SUM(E6:E7) -> 5400000 | F8: =SUM(F6:F7) -> 5400000 | G8: =SUM(G6:G7) -> 5400000 | H8: =SUM(B8:G8) -> 27000000
A10: Costos operativos del utilitario
A11: Seguro | C11: =-12*Supuestos!$B$28 -> -1800000 | D11: =-12*Supuestos!$B$28 -> -1800000 | E11: =-12*Supuestos!$B$28 -> -1800000 | F11: =-12*Supuestos!$B$28 -> -1800000 | G11: =-12*Supuestos!$B$28 -> -1800000 | H11: =SUM(B11:G11) -> -9000000
A12: Patente | C12: =-Supuestos!$B$15*Supuestos!$B$16 -> -749890 | D12: =-Supuestos!$B$15*Supuestos!$B$16 -> -749890 | E12: =-Supuestos!$B$15*Supuestos!$B$16 -> -749890 | F12: =-Supuestos!$B$15*Supuestos!$B$16 -> -749890 | G12: =-Supuestos!$B$15*Supuestos!$B$16 -> -749890 | H12: =SUM(B12:G12) -> -3749450
A13: Mantenimiento | C13: =-IF(1<=2,Supuestos!$B$37,Supuestos!$B$38) -> -600000 | D13: =-IF(2<=2,Supuestos!$B$37,Supuestos!$B$38) -> -600000 | E13: =-IF(3<=2,Supuestos!$B$37,Supuestos!$B$38) -> -1200000 | F13: =-IF(4<=2,Supuestos!$B$37,Supuestos!$B$38) -> -1200000 | G13: =-IF(5<=2,Supuestos!$B$37,Supuestos!$B$38) -> -1200000 | H13: =SUM(B13:G13) -> -4800000
A14: Revisión técnica obligatoria | C14: =-IF(OR(1=3,1=5),Supuestos!$B$17,0) -> 0 | D14: =-IF(OR(2=3,2=5),Supuestos!$B$17,0) -> 0 | E14: =-IF(OR(3=3,3=5),Supuestos!$B$17,0) -> -75000 | F14: =-IF(OR(4=3,4=5),Supuestos!$B$17,0) -> 0 | G14: =-IF(OR(5=3,5=5),Supuestos!$B$17,0) -> -75000 | H14: =SUM(B14:G14) -> -150000
A15: Total costos operativos | C15: =SUM(C11:C14) -> -3149890 | D15: =SUM(D11:D14) -> -3149890 | E15: =SUM(E11:E14) -> -3824890 | F15: =SUM(F11:F14) -> -3749890 | G15: =SUM(G11:G14) -> -3824890 | H15: =SUM(B15:G15) -> -17699450
A17: Resultado operativo antes de amortizaciones | C17: =C8+C15 -> 2250110 | D17: =D8+D15 -> 2250110 | E17: =E8+E15 -> 1575110 | F17: =F8+F15 -> 1650110 | G17: =G8+G15 -> 1575110 | H17: =SUM(B17:G17) -> 9300550
A18: Amortización del utilitario | C18: =-IF(1<=Supuestos!$B$42,Supuestos!$B$8/Supuestos!$B$42,0) -> -6786210 | D18: =-IF(2<=Supuestos!$B$42,Supuestos!$B$8/Supuestos!$B$42,0) -> -6786210 | E18: =-IF(3<=Supuestos!$B$42,Supuestos!$B$8/Supuestos!$B$42,0) -> -6786210 | F18: =-IF(4<=Supuestos!$B$42,Supuestos!$B$8/Supuestos!$B$42,0) -> -6786210 | G18: =-IF(5<=Supuestos!$B$42,Supuestos!$B$8/Supuestos!$B$42,0) -> -6786210 | H18: =SUM(B18:G18) -> -33931050
A19: Resultado operativo | C19: =C17+C18 -> -4536100 | D19: =D17+D18 -> -4536100 | E19: =E17+E18 -> -5211100 | F19: =F17+F18 -> -5136100 | G19: =G17+G18 -> -5211100 | H19: =SUM(B19:G19) -> -24630500
A21: Resultado financiero
A22: Intereses del préstamo INAES (moneda constante) | C22: =-SUMIF('Préstamo INAES'!$B$11:$B$70,1,'Préstamo INAES'!$M$11:$M$70) -> -1648919.7 | D22: =-SUMIF('Préstamo INAES'!$B$11:$B$70,2,'Préstamo INAES'!$M$11:$M$70) -> -1114772 | E22: =-SUMIF('Préstamo INAES'!$B$11:$B$70,3,'Préstamo INAES'!$M$11:$M$70) -> -720973.67 | F22: =-SUMIF('Préstamo INAES'!$B$11:$B$70,4,'Préstamo INAES'!$M$11:$M$70) -> -395225.54 | G22: =-SUMIF('Préstamo INAES'!$B$11:$B$70,5,'Préstamo INAES'!$M$11:$M$70) -> -126532.1 | H22: =SUM(B22:G22) -> -4006423
A23: RECPAM generado por el préstamo | C23: =SUMIF('Préstamo INAES'!$B$11:$B$70,1,'Préstamo INAES'!$P$11:$P$70) -> 5434284.3 | D23: =SUMIF('Préstamo INAES'!$B$11:$B$70,2,'Préstamo INAES'!$P$11:$P$70) -> 2834875.7 | E23: =SUMIF('Préstamo INAES'!$B$11:$B$70,3,'Préstamo INAES'!$P$11:$P$70) -> 1637111.5 | F23: =SUMIF('Préstamo INAES'!$B$11:$B$70,4,'Préstamo INAES'!$P$11:$P$70) -> 897436.78 | G23: =SUMIF('Préstamo INAES'!$B$11:$B$70,5,'Préstamo INAES'!$P$11:$P$70) -> 287315.85 | H23: =SUM(B23:G23) -> 11091024
A24: Bonificación de intereses obtenida | C24: =SUMIF('Préstamo INAES'!$B$11:$B$70,1,'Préstamo INAES'!$O$11:$O$70) -> 0 | D24: =SUMIF('Préstamo INAES'!$B$11:$B$70,2,'Préstamo INAES'!$O$11:$O$70) -> 0 | E24: =SUMIF('Préstamo INAES'!$B$11:$B$70,3,'Préstamo INAES'!$O$11:$O$70) -> 0 | F24: =SUMIF('Préstamo INAES'!$B$11:$B$70,4,'Préstamo INAES'!$O$11:$O$70) -> 0 | G24: =SUMIF('Préstamo INAES'!$B$11:$B$70,5,'Préstamo INAES'!$O$11:$O$70) -> 1291050.4 | H24: =SUM(B24:G24) -> 1291050.4
A25: Gastos iniciales de gestión, patentamiento y garantías | C25: =-Supuestos!$B$39 -> -1500000 | D25: =0 -> 0 | E25: =0 -> 0 | F25: =0 -> 0 | G25: =0 -> 0 | H25: =SUM(B25:G25) -> -1500000
A26: Total resultado financiero | C26: =SUM(C22:C25) -> 2285364.6 | D26: =SUM(D22:D25) -> 1720103.7 | E26: =SUM(E22:E25) -> 916137.86 | F26: =SUM(F22:F25) -> 502211.24 | G26: =SUM(G22:G25) -> 1451834.2 | H26: =SUM(B26:G26) -> 6875651.6
A28: Resultado por venta del utilitario (valor residual − valor contable) | C28: =0 -> 0 | D28: =0 -> 0 | E28: =0 -> 0 | F28: =0 -> 0 | G28: =Supuestos!$B$40*Supuestos!$B$8-(Supuestos!$B$8-MIN(5,Supuestos!$B$42)*Supuestos!$B$8/Supuestos!$B$42) -> 13572420 | H28: =SUM(B28:G28) -> 13572420
A30: Resultado antes de impuestos | C30: =C19+C26+C28 -> -2250735.4 | D30: =D19+D26+D28 -> -2815996.3 | E30: =E19+E26+E28 -> -4294962.1 | F30: =F19+F26+F28 -> -4633888.8 | G30: =G19+G26+G28 -> 9813154.2 | H30: =SUM(B30:G30) -> -4182428.4
A31: Impuesto a las ganancias (exenta, art. 26 inc. d) | C31: =0 -> 0 | D31: =0 -> 0 | E31: =0 -> 0 | F31: =0 -> 0 | G31: =0 -> 0 | H31: =SUM(B31:G31) -> 0
A32: Resultado neto incremental | C32: =C30-C31 -> -2250735.4 | D32: =D30-D31 -> -2815996.3 | E32: =E30-E31 -> -4294962.1 | F32: =F30-F31 -> -4633888.8 | G32: =G30-G31 -> 9813154.2 | H32: =SUM(B32:G32) -> -4182428.4
A34: El IVA no integra el estado de resultados: la cooperativa es responsable inscripta y lo computa como crédito fiscal. El combustible del utilitario se supone igual al de la 4x4 reemplazada.

Sheet Flujo de fondos
A1: Flujo de fondos de la alternativa 3 (moneda constante de septiembre 2026)
A2: Estructura de Sapag Chain (2011). Flujo incremental frente a la situación actual.
A4: Concepto | B4: Año 0 | C4: Año 1 | D4: Año 2 | E4: Año 3 | F4: Año 4 | G4: Año 5 | H4: Total
A5: Flujo del proyecto (sin financiamiento)
A6: Ahorros de costos | C6: =EERR!C8 -> 5400000 | D6: =EERR!D8 -> 5400000 | E6: =EERR!E8 -> 5400000 | F6: =EERR!F8 -> 5400000 | G6: =EERR!G8 -> 5400000 | H6: =SUM(B6:G6) -> 27000000
A7: Costos operativos del utilitario | C7: =EERR!C15 -> -3149890 | D7: =EERR!D15 -> -3149890 | E7: =EERR!E15 -> -3824890 | F7: =EERR!F15 -> -3749890 | G7: =EERR!G15 -> -3824890 | H7: =SUM(B7:G7) -> -17699450
A8: Amortización (gasto no desembolsable) | C8: =EERR!C18 -> -6786210 | D8: =EERR!D18 -> -6786210 | E8: =EERR!E18 -> -6786210 | F8: =EERR!F18 -> -6786210 | G8: =EERR!G18 -> -6786210 | H8: =SUM(B8:G8) -> -33931050
A9: Utilidad antes de impuesto | C9: =SUM(C6:C8) -> -4536100 | D9: =SUM(D6:D8) -> -4536100 | E9: =SUM(E6:E8) -> -5211100 | F9: =SUM(F6:F8) -> -5136100 | G9: =SUM(G6:G8) -> -5211100 | H9: =SUM(B9:G9) -> -24630500
A10: Impuesto a las ganancias (exenta) | C10: =0 -> 0 | D10: =0 -> 0 | E10: =0 -> 0 | F10: =0 -> 0 | G10: =0 -> 0 | H10: =SUM(B10:G10) -> 0
A11: Utilidad neta | C11: =C9-C10 -> -4536100 | D11: =D9-D10 -> -4536100 | E11: =E9-E10 -> -5211100 | F11: =F9-F10 -> -5136100 | G11: =G9-G10 -> -5211100 | H11: =SUM(B11:G11) -> -24630500
A12: Ajuste por amortización | C12: =-C8 -> 6786210 | D12: =-D8 -> 6786210 | E12: =-E8 -> 6786210 | F12: =-F8 -> 6786210 | G12: =-G8 -> 6786210 | H12: =SUM(B12:G12) -> 33931050
A13: Inversión en el utilitario (precio con IVA) | B13: =-Supuestos!B9 -> -37494500 | C13: =0 -> 0 | D13: =0 -> 0 | E13: =0 -> 0 | F13: =0 -> 0 | G13: =0 -> 0 | H13: =SUM(B13:G13) -> -37494500
A14: Gastos iniciales de gestión, patentamiento y garantías | B14: =-Supuestos!B39 -> -1500000 | C14: =0 -> 0 | D14: =0 -> 0 | E14: =0 -> 0 | F14: =0 -> 0 | G14: =0 -> 0 | H14: =SUM(B14:G14) -> -1500000
A15: Recupero del IVA (crédito fiscal) | B15: =0 -> 0 | C15: =Supuestos!B10 -> 3563450 | D15: =0 -> 0 | E15: =0 -> 0 | F15: =0 -> 0 | G15: =0 -> 0 | H15: =SUM(B15:G15) -> 3563450
A16: Valor de desecho (método comercial) | B16: =0 -> 0 | C16: =0 -> 0 | D16: =0 -> 0 | E16: =0 -> 0 | F16: =0 -> 0 | G16: =Supuestos!B40*Supuestos!B8 -> 13572420 | H16: =SUM(B16:G16) -> 13572420
A17: Flujo de fondos del proyecto | B17: =SUM(B13:B16) -> -38994500 | C17: =C11+C12+SUM(C13:C16) -> 5813560 | D17: =D11+D12+SUM(D13:D16) -> 2250110 | E17: =E11+E12+SUM(E13:E16) -> 1575110 | F17: =F11+F12+SUM(F13:F16) -> 1650110 | G17: =G11+G12+SUM(G13:G16) -> 15147530 | H17: =SUM(B17:G17) -> -12558080
A19: Financiamiento INAES
A20: Préstamo recibido | B20: ='Préstamo INAES'!E3 -> 33931050 | C20: =0 -> 0 | D20: =0 -> 0 | E20: =0 -> 0 | F20: =0 -> 0 | G20: =0 -> 0 | H20: =SUM(B20:G20) -> 33931050
A21: Intereses pagados (moneda constante) | C21: =-SUMIF('Préstamo INAES'!$B$11:$B$70,1,'Préstamo INAES'!$M$11:$M$70) -> -1648919.7 | D21: =-SUMIF('Préstamo INAES'!$B$11:$B$70,2,'Préstamo INAES'!$M$11:$M$70) -> -1114772 | E21: =-SUMIF('Préstamo INAES'!$B$11:$B$70,3,'Préstamo INAES'!$M$11:$M$70) -> -720973.67 | F21: =-SUMIF('Préstamo INAES'!$B$11:$B$70,4,'Préstamo INAES'!$M$11:$M$70) -> -395225.54 | G21: =-SUMIF('Préstamo INAES'!$B$11:$B$70,5,'Préstamo INAES'!$M$11:$M$70) -> -126532.1 | H21: =SUM(B21:G21) -> -4006423
A22: Amortización del capital (moneda constante) | C22: =-SUMIF('Préstamo INAES'!$B$11:$B$70,1,'Préstamo INAES'!$N$11:$N$70) -> -5424769 | D22: =-SUMIF('Préstamo INAES'!$B$11:$B$70,2,'Préstamo INAES'!$N$11:$N$70) -> -4849956 | E22: =-SUMIF('Préstamo INAES'!$B$11:$B$70,3,'Préstamo INAES'!$N$11:$N$70) -> -4500355.4 | F22: =-SUMIF('Préstamo INAES'!$B$11:$B$70,4,'Préstamo INAES'!$N$11:$N$70) -> -4180873.6 | G22: =-SUMIF('Préstamo INAES'!$B$11:$B$70,5,'Préstamo INAES'!$N$11:$N$70) -> -3884071.8 | H22: =SUM(B22:G22) -> -22840026
A23: Bonificación aplicada a las últimas cuotas | C23: =SUMIF('Préstamo INAES'!$B$11:$B$70,1,'Préstamo INAES'!$O$11:$O$70) -> 0 | D23: =SUMIF('Préstamo INAES'!$B$11:$B$70,2,'Préstamo INAES'!$O$11:$O$70) -> 0 | E23: =SUMIF('Préstamo INAES'!$B$11:$B$70,3,'Préstamo INAES'!$O$11:$O$70) -> 0 | F23: =SUMIF('Préstamo INAES'!$B$11:$B$70,4,'Préstamo INAES'!$O$11:$O$70) -> 0 | G23: =SUMIF('Préstamo INAES'!$B$11:$B$70,5,'Préstamo INAES'!$O$11:$O$70) -> 1291050.4 | H23: =SUM(B23:G23) -> 1291050.4
A24: Flujo de fondos del inversionista (cooperativa) | B24: =B17+SUM(B20:B23) -> -5063450 | C24: =C17+SUM(C20:C23) -> -1260128.7 | D24: =D17+SUM(D20:D23) -> -3714618 | E24: =E17+SUM(E20:E23) -> -3646219.1 | F24: =F17+SUM(F20:F23) -> -2925989.1 | G24: =G17+SUM(G20:G23) -> 12427976 | H24: =SUM(B24:G24) -> -4182428.4
A26: Flujos acumulados
A27: Proyecto: acumulado | B27: =B17 -> -38994500 | C27: =B27+C17 -> -33180940 | D27: =C27+D17 -> -30930830 | E27: =D27+E17 -> -29355720 | F27: =E27+F17 -> -27705610 | G27: =F27+G17 -> -12558080
A28: Proyecto: acumulado descontado | B28: =B17 -> -38994500 | C28: =B28+C17/(1+Supuestos!$B$27)^1 -> -33457776 | D28: =C28+D17/(1+Supuestos!$B$27)^2 -> -31416860 | E28: =D28+E17/(1+Supuestos!$B$27)^3 -> -30056221 | F28: =E28+F17/(1+Supuestos!$B$27)^4 -> -28698671 | G28: =F28+G17/(1+Supuestos!$B$27)^5 -> -16830185
A29: Inversionista: acumulado | B29: =B24 -> -5063450 | C29: =B29+C24 -> -6323578.7 | D29: =C29+D24 -> -10038197 | E29: =D29+E24 -> -13684416 | F29: =E29+F24 -> -16610405 | G29: =F29+G24 -> -4182428.4
A30: Inversionista: acumulado descontado | B30: =B24 -> -5063450 | C30: =B30+C24/(1+Supuestos!$B$27)^1 -> -6263572.6 | D30: =C30+D24/(1+Supuestos!$B$27)^2 -> -9632840.6 | E30: =D30+E24/(1+Supuestos!$B$27)^3 -> -12782582 | F30: =E30+F24/(1+Supuestos!$B$27)^4 -> -15189800 | G30: =F30+G24/(1+Supuestos!$B$27)^5 -> -5452155.5
A31: Auxiliar: recupero del proyecto | C31: =IF(AND(B27<0,C27>=0),0+(-B27)/(C17),"") | D31: =IF(AND(C27<0,D27>=0),1+(-C27)/(D17),"") | E31: =IF(AND(D27<0,E27>=0),2+(-D27)/(E17),"") | F31: =IF(AND(E27<0,F27>=0),3+(-E27)/(F17),"") | G31: =IF(AND(F27<0,G27>=0),4+(-F27)/(G17),"")
A32: Auxiliar: recupero descontado del proyecto | C32: =IF(AND(B28<0,C28>=0),0+(-B28)/(C17/(1+Supuestos!$B$27)^1),"") | D32: =IF(AND(C28<0,D28>=0),1+(-C28)/(D17/(1+Supuestos!$B$27)^2),"") | E32: =IF(AND(D28<0,E28>=0),2+(-D28)/(E17/(1+Supuestos!$B$27)^3),"") | F32: =IF(AND(E28<0,F28>=0),3+(-E28)/(F17/(1+Supuestos!$B$27)^4),"") | G32: =IF(AND(F28<0,G28>=0),4+(-F28)/(G17/(1+Supuestos!$B$27)^5),"")
A33: Auxiliar: recupero del inversionista | C33: =IF(AND(B29<0,C29>=0),0+(-B29)/(C24),"") | D33: =IF(AND(C29<0,D29>=0),1+(-C29)/(D24),"") | E33: =IF(AND(D29<0,E29>=0),2+(-D29)/(E24),"") | F33: =IF(AND(E29<0,F29>=0),3+(-E29)/(F24),"") | G33: =IF(AND(F29<0,G29>=0),4+(-F29)/(G24),"")
A34: Auxiliar: recupero descontado del inversionista | C34: =IF(AND(B30<0,C30>=0),0+(-B30)/(C24/(1+Supuestos!$B$27)^1),"") | D34: =IF(AND(C30<0,D30>=0),1+(-C30)/(D24/(1+Supuestos!$B$27)^2),"") | E34: =IF(AND(D30<0,E30>=0),2+(-D30)/(E24/(1+Supuestos!$B$27)^3),"") | F34: =IF(AND(E30<0,F30>=0),3+(-E30)/(F24/(1+Supuestos!$B$27)^4),"") | G34: =IF(AND(F30<0,G30>=0),4+(-F30)/(G24/(1+Supuestos!$B$27)^5),"")
A36: Indicadores (tasa de descuento real) | B36: Proyecto | C36: Inversionista
A37: Tasa de descuento real anual | B37: =Supuestos!$B$27 -> 0.05 | C37: =Supuestos!$B$27 -> 0.05
A38: Valor actual neto (VAN) | B38: =B17+NPV(Supuestos!$B$27,C17:G17) -> -16830185 | C38: =B24+NPV(Supuestos!$B$27,C24:G24) -> -5452155.5
A39: Tasa interna de retorno (TIR) | B39: =IFERROR(IRR(B17:G17),"No existe") -> -0.096688852 | C39: =IFERROR(IRR(B24:G24),"No existe") -> -0.091938491
A40: TIR modificada (reinversión a la tasa de descuento) | B40: =MIRR(B17:G17,Supuestos!$B$27,Supuestos!$B$27) -> -0.062180001 | C40: =MIRR(B24:G24,Supuestos!$B$27,Supuestos!$B$27) -> -0.039340079
A41: Período de recupero simple (años) | B41: =IF(COUNT(C31:G31)=0,"No se recupera",MIN(C31:G31)) -> No se recupera | C41: =IF(COUNT(C33:G33)=0,"No se recupera",MIN(C33:G33)) -> No se recupera
A42: Período de recupero descontado (años) | B42: =IF(COUNT(C32:G32)=0,"No se recupera",MIN(C32:G32)) -> No se recupera | C42: =IF(COUNT(C34:G34)=0,"No se recupera",MIN(C34:G34)) -> No se recupera
A44: Valor del financiamiento INAES (VAN inversionista − VAN proyecto) | B44: =C38-B38 -> 11378030
A46: El flujo del inversionista es negativo en los años 0 a 4 y solo se vuelve positivo en el año 5; se informa también la TIR modificada.

Sheet Sensibilidad
A1: Análisis de sensibilidad (se modifica un supuesto por vez)
A2: Valores estáticos: surgen de recalcular el modelo con el supuesto indicado. Para otros escenarios, modificar la hoja Supuestos.
A4: Escenario | B4: VAN proyecto | C4: VAN inversionista | D4: TIR inversionista
A5: Caso base | B5: -16830185 | C5: -5452155 | D5: -0.091938491
A6: El utilitario reemplaza a ambos vehículos (pago y combustible del vehículo 1) | B6: 11744361 | C6: 23122391 | D6: 0.90488905
A7: Valor residual nulo (método contable) | B7: -27464531 | C7: -16086502 | D7: No existe
A8: Valor residual 25 % | B8: -20818065 | C8: -9440035 | D8: -0.25302051
A9: Valor residual 55 % | B9: -12842305 | C9: -1464276 | D9: 0.017121658
A10: Tasa de descuento real 3 % | B10: -15255380 | C10: -5004288 | D10: -0.091938491
A11: Tasa de descuento real 10 % | B11: -20133975 | C11: -6300106 | D11: -0.091938491
A12: Inflación de 10 % anual desde 2027 | B12: -16830185 | C12: -8082957 | D12: -0.15780208
A13: Pérdida de la bonificación por mora | B13: -16830185 | C13: -6463727 | D13: -0.12608916
A14: Tipo de cambio 10 % mayor al comprar | B14: -19501487 | C14: -6985655 | D14: -0.11413267
A15: Seguro todo riesgo ($250.000 mensuales) | B15: -22025557 | C15: -10647527 | D15: -0.20987264
A16: Mantenimiento 50 % mayor | B16: -18870048 | C16: -7492018 | D16: -0.14358068
A17: Patente como camión (1,5 %) | B17: -16018527 | C17: -4640498 | D17: -0.07209198
A19: Valores críticos (VAN = 0)
A20: Valor residual mínimo para VAN del inversionista = 0 (% del precio neto) | B20: 0.6051
A21: Pago mensual por la 4x4 que hace VAN del proyecto = 0 | B21: 773946
A22: Pago mensual por la 4x4 que hace VAN del inversionista = 0 | B22: 554943
